bert/__init__.py
bert/attention.py
bert/bert.py
bert/bert_model.py
bert/embedding.py
bert/gelu.py
bert/pool.py
bert/pred.py
bert/transformer.py
bert/utils.py
bert/tests/__init__.py
bert/tests/attention.py
bert/tests/bert.py
bert/tests/compare_official.py
bert/tests/config.py
bert/tests/convert_albert.py
bert/tests/convert_electra.py
bert/tests/convert_official.py
bert/tests/embedding.py
bert/tests/pool.py
bert/tests/pred.py
bert/tests/train.py
bert/tests/train_custom.py
bert/tests/train_fp16.py
bert/tests/transformer.py
tfbert-0.2.4.dist-info/LICENSE
tfbert-0.2.4.dist-info/METADATA
tfbert-0.2.4.dist-info/WHEEL
tfbert-0.2.4.dist-info/top_level.txt
tfbert-0.2.4.dist-info/RECORD
